{
    "Items": [
        {
            "name": "",
            "position": {
                "x": 0.0,
                "y": 0.0,
                "z": 0.0
            },
            "rotation": {
                "x": 0.0,
                "y": 0.0,
                "z": 0.0,
                "w": 0.0
            },
            "scale": {
                "x": 0.0,
                "y": 0.0,
                "z": 0.0
            },
            "prefabPath": ""
        },
        {
            "name": "",
            "position": {
                "x": 0.0,
                "y": 0.0,
                "z": 0.0
            },
            "rotation": {
                "x": 0.0,
                "y": 0.0,
                "z": 0.0,
                "w": 0.0
            },
            "scale": {
                "x": 0.0,
                "y": 0.0,
                "z": 0.0
            },
            "prefabPath": ""
        },
        {
            "name": "Cube (1)",
            "position": {
                "x": 1.1200000047683716,
                "y": 0.75,
                "z": -0.5899999737739563
            },
            "rotation": {
                "x": 0.0,
                "y": 0.0,
                "z": 0.0,
                "w": 1.0
            },
            "scale": {
                "x": 0.28404998779296877,
                "y": 0.28404998779296877,
                "z": 0.28404998779296877
            },
            "prefabPath": ""
        },
        {
            "name": "",
            "position": {
                "x": 0.0,
                "y": 0.0,
                "z": 0.0
            },
            "rotation": {
                "x": 0.0,
                "y": 0.0,
                "z": 0.0,
                "w": 0.0
            },
            "scale": {
                "x": 0.0,
                "y": 0.0,
                "z": 0.0
            },
            "prefabPath": ""
        },
        {
            "name": "Tree",
            "position": {
                "x": -0.5600000023841858,
                "y": 0.5699999928474426,
                "z": -0.6800000071525574
            },
            "rotation": {
                "x": 0.0,
                "y": 0.0,
                "z": 0.0,
                "w": 1.0
            },
            "scale": {
                "x": 0.3303399980068207,
                "y": 1.0,
                "z": 0.3196899890899658
            },
            "prefabPath": ""
        },
        {
            "name": "Plane",
            "position": {
                "x": -8.145899772644043,
                "y": -3.3087000846862795,
                "z": 10.09469985961914
            },
            "rotation": {
                "x": 0.0,
                "y": 0.0,
                "z": 0.0,
                "w": 1.0
            },
            "scale": {
                "x": 5.619473457336426,
                "y": 1.0,
                "z": 7.508884429931641
            },
            "prefabPath": ""
        },
        {
            "name": "MiniIsland2",
            "position": {
                "x": -0.4300000071525574,
                "y": -0.0010000000474974514,
                "z": 1.5169999599456788
            },
            "rotation": {
                "x": 0.0,
                "y": 0.0,
                "z": 0.0,
                "w": 1.0
            },
            "scale": {
                "x": 1.6043403148651124,
                "y": 0.0903211161494255,
                "z": 1.6689319610595704
            },
            "prefabPath": ""
        },
        {
            "name": "MiniIsland",
            "position": {
                "x": 2.0190000534057619,
                "y": -0.0010000000474974514,
                "z": -0.05000000074505806
            },
            "rotation": {
                "x": 0.0,
                "y": 0.0,
                "z": 0.0,
                "w": 1.0
            },
            "scale": {
                "x": 1.6043403148651124,
                "y": 0.0903211161494255,
                "z": 1.6689319610595704
            },
            "prefabPath": ""
        },
        {
            "name": "MainIsland",
            "position": {
                "x": 0.0,
                "y": 0.0,
                "z": -0.05000000074505806
            },
            "rotation": {
                "x": 0.0,
                "y": 0.0,
                "z": 0.0,
                "w": 1.0
            },
            "scale": {
                "x": 3.292173385620117,
                "y": 0.41839975118637087,
                "z": 3.424718141555786
            },
            "prefabPath": ""
        },
        {
            "name": "Cube",
            "position": {
                "x": 0.2199999988079071,
                "y": 0.5400000214576721,
                "z": 0.7200000286102295
            },
            "rotation": {
                "x": 0.0,
                "y": 0.0,
                "z": 0.0,
                "w": 1.0
            },
            "scale": {
                "x": 0.5580599904060364,
                "y": 0.5580599904060364,
                "z": 0.5580599904060364
            },
            "prefabPath": ""
        }
    ]
}